pylipsync/__init__.py
pylipsync/analyzer.py
pylipsync/similarity.py
pylipsync/types.py
pylipsync/phonemes/template.json
pylipsync/phonemes/audio/aa/A_female.mp3
pylipsync/phonemes/audio/ee/E_female.mp3
pylipsync/phonemes/audio/ih/I_female.mp3
pylipsync/phonemes/audio/oh/O_female.mp3
pylipsync/phonemes/audio/ou/U_female.mp3
pylipsync/phonemes/audio/silence/silence.mp3
pylipsync/utils/__init__.py
pylipsync/utils/audio.py
pylipsync/utils/feature_extraction.py
pylipsync-0.2.1.dist-info/licenses/LICENSE
pylipsync-0.2.1.dist-info/METADATA
pylipsync-0.2.1.dist-info/WHEEL
pylipsync-0.2.1.dist-info/top_level.txt
pylipsync-0.2.1.dist-info/RECORD
