Metadata-Version: 2.4
Name: pylipsync
Version: 0.2.1
Summary: A Python implementation of Hecomi's uLipSync for audio-based lip sync analysis.
License: MIT
Project-URL: Homepage, https://github.com/spava002/pyLipSync
Keywords: lip-sync,audio,phoneme,mfcc,speech-analysis,animation
Classifier: Development Status :: 4 - Beta
Classifier: Intended Audience :: Developers
Classifier: Topic :: Multimedia :: Sound/Audio :: Analysis
Classifier: Programming Language :: Python :: 3.9
Classifier: Programming Language :: Python :: 3.10
Classifier: Programming Language :: Python :: 3.11
Classifier: Programming Language :: Python :: 3.12
Classifier: License :: OSI Approved :: MIT License
Classifier: Operating System :: OS Independent
Requires-Python: >=3.9
License-File: LICENSE
Requires-Dist: librosa>=0.10.0
Requires-Dist: numpy<2.4.0,>=1.20.0
Requires-Dist: scipy>=1.7.0
Dynamic: license-file
